abstract_webserver/__init__.py
abstract_webserver/abstract_types.py
abstract_webserver/abstract_webserver.py
abstract_webserver/directory_processor.py
abstract_webserver/get_image_json.py
abstract_webserver/get_source.py
abstract_webserver/json_convention.py
abstract_webserver/path_utils.py
abstract_webserver/serverManager.py
abstract_webserver/social_media.py
abstract_webserver/social_media_utils.py
abstract_webserver/auth_utils/__init__.py
abstract_webserver/auth_utils/create_user.py
abstract_webserver/auth_utils/login_utils.py
abstract_webserver/auth_utils/pass_utils.py
abstract_webserver/auth_utils/query_utils.py
abstract_webserver/auth_utils/token_utils.py
abstract_webserver/auth_utils/user_store/__init__.py
abstract_webserver/auth_utils/user_store/admin_utils.py
abstract_webserver/auth_utils/user_store/blacklist_utils.py
abstract_webserver/auth_utils/user_store/table_utils.py
abstract_webserver/auth_utils/user_store/users_utils.py
abstract_webserver-0.0.0.42.dist-info/METADATA
abstract_webserver-0.0.0.42.dist-info/WHEEL
abstract_webserver-0.0.0.42.dist-info/top_level.txt
abstract_webserver-0.0.0.42.dist-info/RECORD
