Metadata-Version: 2.4
Name: abstract_webserver
Version: 0.0.0.42
Summary: abstract_webserver
Home-page: https://github.com/AbstractEndeavors/abstract_webserver
Author: putkoff
Author-email: partners@abstractendeavors.com
Classifier: Development Status :: 3 - Alpha
Classifier: Intended Audience :: Developers
Classifier: License :: OSI Approved :: MIT License
Classifier: Programming Language :: Python :: 3
Classifier: Programming Language :: Python :: 3.11
Requires-Python: >=3.6
Requires-Dist: pexpect>=4.8.0
Requires-Dist: abstract_security>=0.0.1
Dynamic: author
Dynamic: author-email
Dynamic: classifier
Dynamic: description
Dynamic: description-content-type
Dynamic: home-page
Dynamic: requires-dist
Dynamic: requires-python
Dynamic: summary
